refined/__init__.py
refined/__main__.py
refined/decorator.py
refined/refinement_types.py
refined/plugins/__init__.py
refined/predicates/__init__.py
refined/predicates/base.py
refined/predicates/collection.py
refined/predicates/common.py
refined/predicates/generic.py
refined/predicates/numeric.py
refined/predicates/string.py
refined-0.0.1.dist-info/LICENSE
refined-0.0.1.dist-info/METADATA
refined-0.0.1.dist-info/WHEEL
refined-0.0.1.dist-info/top_level.txt
refined-0.0.1.dist-info/RECORD
