Metadata-Version: 2.1
Name: refined
Version: 0.0.1
Summary: Refinement type hints for Python
Home-page: https://github.com/espetro/refined
Author: Quino Terrasa and collaborators
Author-email: quino.terrasa+refined@gmail.com
License: UNKNOWN
Platform: UNKNOWN
Classifier: Programming Language :: Python :: 3
Classifier: Programming Language :: Python :: 3.7
Classifier: Programming Language :: Python :: 3.8
Classifier: Programming Language :: Python :: 3.9
Classifier: Programming Language :: Python :: 3.10
Requires-Python: >=3.7
Requires-Dist: typing-extensions (~=3.10)
